[
  {
    "Id": "680727",
    "ThreadId": "274958",
    "Html": "\r\n<p>Hi,&nbsp;</p>\r\n<p>I am using Wpf Toolkit for the graph, and I realise that it doesn't work when I place it as the second tabitem. What could be the problem?</p>\r\n<p>This is my graph:</p>\r\n<p>&nbsp;</p>\r\n<p>&lt;TabControl&gt;</p>\r\n<p>&nbsp; &nbsp; &nbsp; &nbsp; &lt;TabItem Header=&quot;PowerFlow&quot;&gt;</p>\r\n<p>&nbsp; &nbsp; &nbsp; &nbsp; &lt;/TabItem&gt;</p>\r\n<p>&nbsp; &nbsp; &nbsp; &nbsp; &lt;TabItem Header=&quot;Graph&quot; Name=&quot;Graphs&quot;&gt;</p>\r\n<p>&nbsp; &nbsp; &nbsp; &nbsp; &nbsp; &nbsp; &lt;ScrollViewer HorizontalScrollBarVisibility=&quot;Auto&quot;&nbsp;</p>\r\n<p><span>&nbsp;</span><span> </span>&nbsp;VerticalScrollBarVisibility=&quot;Auto&quot; Margin=&quot;0,-28,0,28&quot;&gt;</p>\r\n<p>&nbsp; &nbsp; &nbsp; &nbsp; &nbsp; &nbsp; &nbsp; &nbsp; &lt;Grid Height=&quot;921&quot; Background=&quot;DarkGray&quot;&gt;</p>\r\n<p>&nbsp; &nbsp; &nbsp; &nbsp; &nbsp; &nbsp; &nbsp; &nbsp; &nbsp; &nbsp; &lt;chartingToolkit:Chart &nbsp;Name=&quot;lineChart&quot; Title=&quot;Power Graph&quot; Background=&quot;YellowGreen&quot;&nbsp;Foreground=&quot;DarkBlue&quot; &nbsp; &nbsp; &nbsp; &nbsp; &nbsp; &nbsp; &nbsp; &nbsp; &nbsp;&nbsp;<span>\r\n</span>&nbsp; VerticalAlignment=&quot;Top&quot; Margin=&quot;16,36,20,0&quot; Height=&quot;432&quot; &nbsp;IsEnabled=&quot;True&quot; &gt;</p>\r\n<p>&nbsp; &nbsp; &nbsp; &nbsp; &nbsp; &nbsp; &nbsp; &nbsp; &nbsp; &nbsp; &nbsp; &nbsp; &lt;chartingToolkit:LineSeries Title=&quot;SolarCell&quot;&nbsp;</p>\r\n<p><span>&nbsp;</span>&nbsp; &nbsp;<span> </span>ItemsSource=&quot;{Binding}&quot;&nbsp;DependentValueBinding=&quot;{Binding Path=Value}&quot;&nbsp;</p>\r\n<p>IndependentValueBinding=&quot;{Binding Path=Key}&quot;</p>\r\n<p>&nbsp; &nbsp; &nbsp; &nbsp; &nbsp; &nbsp;<span> </span>&nbsp;IsSelectionEnabled=&quot;True&quot; DataContext=&quot;{Binding}&quot;&gt;</p>\r\n<p>&nbsp; &nbsp; &nbsp; &nbsp; &nbsp; &nbsp; &nbsp; &nbsp; &nbsp; &nbsp; &nbsp; &nbsp; &nbsp; &nbsp; &lt;chartingToolkit:LineSeries.DependentRangeAxis&gt;</p>\r\n<p>&nbsp; &nbsp; &nbsp; &nbsp; &nbsp; &nbsp; &nbsp; &nbsp; &nbsp; &nbsp; &nbsp; &nbsp; &nbsp; &nbsp; &nbsp; &nbsp; &lt;chartingToolkit:LinearAxis Orientation=&quot;Y&quot; Title=&quot;Power (W)&quot;&gt;&lt;/chartingToolkit:LinearAxis&gt;</p>\r\n<p>&nbsp; &nbsp; &nbsp; &nbsp; &nbsp; &nbsp; &nbsp; &nbsp; &nbsp; &nbsp; &nbsp; &nbsp; &nbsp; &nbsp; &lt;/chartingToolkit:LineSeries.DependentRangeAxis&gt;</p>\r\n<p>&nbsp; &nbsp; &nbsp; &nbsp; &nbsp; &nbsp; &nbsp; &nbsp; &nbsp; &nbsp; &nbsp; &nbsp; &lt;/chartingToolkit:LineSeries&gt;</p>\r\n<p>&nbsp; &nbsp; &nbsp; &nbsp; &nbsp; &nbsp; &nbsp; &nbsp; &nbsp; &nbsp; &lt;/chartingToolkit:Chart&gt;</p>\r\n<p>&nbsp; &nbsp; &nbsp; &nbsp; &nbsp; &nbsp; &nbsp; &nbsp; &nbsp; &nbsp; &lt;Button Content=&quot;Refresh&quot; Height=&quot;23&quot; HorizontalAlignment=&quot;Left&quot; Margin=&quot;718,391,0,0&quot; Name=&quot;button1&quot;&nbsp;VerticalAlignment=&quot;Top&quot; Width=&quot;75&quot; /&gt;</p>\r\n<p>&nbsp; &nbsp; &nbsp; &nbsp; &nbsp; &nbsp; &nbsp; &nbsp; &nbsp; &nbsp; &lt;TextBox Height=&quot;23&quot; HorizontalAlignment=&quot;Left&quot; Margin=&quot;696,73,0,0&quot; Name=&quot;textBox7&quot; VerticalAlignment=&quot;Top&quot;&nbsp;Width=&quot;97&quot; Loaded=&quot;textBox7_Loaded&quot; /&gt;</p>\r\n<p>&nbsp; &nbsp; &nbsp; &nbsp; &nbsp; &nbsp; &nbsp; &nbsp; &nbsp; &nbsp; &lt;Label Content=&quot;Time started:&quot; Height=&quot;28&quot; HorizontalAlignment=&quot;Left&quot; Margin=&quot;606,73,0,0&quot; Name=&quot;label1&quot;&nbsp;VerticalAlignment=&quot;Top&quot; Width=&quot;84&quot; /&gt;</p>\r\n<p>&nbsp; &nbsp; &nbsp; &nbsp; &nbsp; &nbsp; &nbsp; &nbsp; &lt;/Grid&gt;</p>\r\n<p>&nbsp; &nbsp; &nbsp; &nbsp; &nbsp; &nbsp; &lt;/ScrollViewer&gt;</p>\r\n<p>&nbsp; &nbsp; &nbsp; &nbsp; &lt;/TabItem&gt;</p>\r\n<p>&nbsp; &nbsp; &lt;/TabControl&gt;</p>\r\n<p>&lt;/Window&gt;</p>\r\n<p>&nbsp;</p>\r\n<p>&nbsp;</p>\r\n<p>&nbsp;</p>\r\n<p>&nbsp;</p>\r\n",
    "PostedDate": "2011-10-06T03:52:23.717-07:00",
    "UserRole": null,
    "MarkedAsAnswerDate": null
  },
  {
    "Id": "712962",
    "ThreadId": "274958",
    "Html": "<p>i think u have binding issue. The UI doesn't get binded I suggest put break point and recheck code</p>",
    "PostedDate": "2011-12-15T15:17:42.25-08:00",
    "UserRole": null,
    "MarkedAsAnswerDate": null
  }
]