[
  {
    "Id": "769874",
    "ThreadId": "318259",
    "Html": "\r\n<p><span style=\"color:#000000; font-family:Arial,'Liberation Sans','DejaVu Sans',sans-serif; font-size:14px; font-style:normal; font-variant:normal; font-weight:normal; letter-spacing:normal; line-height:18px; orphans:2; text-align:left; text-indent:0px; text-transform:none; white-space:normal; widows:2; word-spacing:0px; background-color:#ffffff; display:inline!important; float:none\">I\r\n have a requirement, where the user has the ability to select multiple cells (row wise or column Wise). As soon as the selection is complete I need to merge only the selected cells(not the entire row or column). I did some research online, many suggested grouping.\r\n But when I use grouping entire row is getting merged. Can you guys please help me with this issue.</span></p>\r\n",
    "PostedDate": "2012-02-16T08:52:27.64-08:00",
    "UserRole": null,
    "MarkedAsAnswerDate": null
  }
]