[
  {
    "Id": "126546",
    "ThreadId": "38159",
    "Html": "Hi, I would like to implement multi selection without using the ctrl key, etc.&nbsp;<br>\r\n<br>\r\nAlso, I would like the last selected row, to be a different color then the previous selected rows, is this possible with this version of the grid?<br>\r\n<br>\r\nThanks for your time\r\n",
    "PostedDate": "2008-10-21T08:03:25.613-07:00",
    "UserRole": null,
    "MarkedAsAnswerDate": null
  },
  {
    "Id": "129925",
    "ThreadId": "38159",
    "Html": "The first request will be really hard as that functionality is sort of hard coded in DataGrid.cs.  <br>\r\n<br>\r\nThe second request is possible.  Note that DataGridCell also creates a background color on selected rows so you will need to remove that.  What you can do is listen for the CurrentItem changing and when it is the last row set the background.  You can also do it in xaml with the row's background bound to IsSelected with a converter that also checks if it's the last row.\r\n",
    "PostedDate": "2008-11-04T05:57:03.373-08:00",
    "UserRole": null,
    "MarkedAsAnswerDate": null
  }
]