[
  {
    "Id": "156355",
    "ThreadId": "46762",
    "Html": "<p style=\"margin:0cm 0cm 0pt\"><span style=\"color:black;font-family:'courier new'\">Someone have an idea, an example or if I speak in another discussion on transforming the rows and columns per head to have them on the first row. <br>\r\n</span><span style=\"color:black;font-family:'courier new'\"><br>\r\nAny idea is welcome.</span></p>\r\n",
    "PostedDate": "2009-02-10T11:28:09.72-08:00",
    "UserRole": null,
    "MarkedAsAnswerDate": null
  }
]