[
  {
    "Id": "158353",
    "ThreadId": "47315",
    "Html": "I am populating a datagrid with data from linq.  This works great, except clicking on the column header does not sort the column.  The column header shows the sort direction arrow, but the contents are not sorted.  How can I get the sort function to work?  Here is the code I am using to load the datagrid.<br>\r\n<br>\r\n<span style=\"font-size:10px;color:#0000ff\"><span style=\"font-size:10px;color:#0000ff\">\r\n<p>Private</p>\r\n</span>\r\n<p>&nbsp;</p>\r\n</span>\r\n<p><span style=\"font-size:10px\"> </span><span style=\"font-size:10px;color:#0000ff\">Sub</span><span style=\"font-size:10px\"> LoadGrid()\r\n<p>&nbsp;</p>\r\n<p>&nbsp;</p>\r\n</span></p>\r\n<p><span style=\"font-size:10px;color:#0000ff\">Dim</span><span style=\"font-size:10px\"> lang = </span><span style=\"font-size:10px;color:#0000ff\">From</span><span style=\"font-size:10px\"> p </span><span style=\"font-size:10px;color:#0000ff\">In</span><span style=\"font-size:10px\"> db.LanguageText </span><span style=\"font-size:10px;color:#0000ff\">Order</span><span style=\"font-size:10px\"> </span><span style=\"font-size:10px;color:#0000ff\">By</span><span style=\"font-size:10px\"> p.SpanishText </span><span style=\"font-size:10px;color:#0000ff\">Select</span><span style=\"font-size:10px\"> p.SpanishText, p.EnglishText\r\n<p>&nbsp;</p>\r\n<p>spanishGrid.ItemsSource = lang</p>\r\n<p>spanishGrid.Columns(0).Header = </p>\r\n</span></p>\r\n<p><span style=\"font-size:10px;color:#a31515\">&quot;Spanish&quot;\r\n<p>&nbsp;</p>\r\n</span></p>\r\n<span style=\"font-size:10px\">\r\n<p>spanishGrid.Columns(0).MinWidth = 100</p>\r\n<p>spanishGrid.Columns(1).Header = </p>\r\n</span>\r\n<p><span style=\"font-size:10px;color:#a31515\">&quot;English&quot;\r\n<p>&nbsp;</p>\r\n</span></p>\r\n<span style=\"font-size:10px\">\r\n<p>spanishGrid.Columns(1).MinWidth = 100</p>\r\n<p>&nbsp;</p>\r\n</span>\r\n<p><span style=\"font-size:10px;color:#0000ff\">End</span><span style=\"font-size:10px\"> </span><span style=\"font-size:10px;color:#0000ff\">Sub<br>\r\n<p>&nbsp;</p>\r\n</span></p>\r\n",
    "PostedDate": "2009-02-16T19:48:17.943-08:00",
    "UserRole": null,
    "MarkedAsAnswerDate": null
  },
  {
    "Id": "158625",
    "ThreadId": "47315",
    "Html": "Hi John_s,<br>\r\n<br>\r\nThis is a known issue.  Please see this page for more information: <a href=\"http://www.codeplex.com/wpf/Wiki/View.aspx?title=Data Sources&referringTitle=Tips %26 Tricks\">http://www.codeplex.com/wpf/Wiki/View.aspx?title=Data%20Sources&amp;referringTitle=Tips%20%26%20Tricks</a><br>\r\n<br>\r\nThanks,<br>\r\nSamantha<br>\r\n",
    "PostedDate": "2009-02-17T12:09:29.51-08:00",
    "UserRole": null,
    "MarkedAsAnswerDate": null
  },
  {
    "Id": "158633",
    "ThreadId": "47315",
    "Html": "<p>Thanks Samantha.  I am not using linq to SQL, I am using linq to an entity.</p>\r\n<p>shared db As New spanishEntities</p>\r\n<p>spanishEntities is my EntityContainer.  Based on the known issues page you referred me to, shouldn't this work?</p>\r\n<p>John<br>\r\n</p>\r\n",
    "PostedDate": "2009-02-17T12:25:27.53-08:00",
    "UserRole": null,
    "MarkedAsAnswerDate": null
  },
  {
    "Id": "159840",
    "ThreadId": "47315",
    "Html": "Hi John,<br>\r\n<br>\r\nI believe that LINQ to Entity has the same problem.  Any data source which returns an IBindingList will break our built-in sort.<br>\r\n<br>\r\nThanks,<br>\r\nSamantha\r\n",
    "PostedDate": "2009-02-19T11:40:28.96-08:00",
    "UserRole": null,
    "MarkedAsAnswerDate": null
  },
  {
    "Id": "160689",
    "ThreadId": "47315",
    "Html": "Hi,<br>\r\n<br>\r\nI have the same problem.<br>\r\n<br>\r\nWill it be fixed soon?<br>\r\n<br>\r\nBest regards <br>\r\n<br>\r\nToni \r\n",
    "PostedDate": "2009-02-22T13:03:01.39-08:00",
    "UserRole": null,
    "MarkedAsAnswerDate": null
  }
]