[
  {
    "Id": "190671",
    "ThreadId": "56428",
    "Html": "<p>Hello All,<br> <br> I have used Microsoft Window Ribbon Control(Similar to Microsoft Office) in almost all the form that I have created. That works great but, now I have changed the design color(Applied some themes) of all the components that I have used. But I am not able to change the Default &quot;Blue&quot; color of the Ribbon Control which can be seen above the MenuBar.</p>\r\n<p>In short, I want to change the <span style=\"text-decoration:underline\">BLUE COLOR </span>SEEN AT THE TOP OF THE WINDOW.</p>\r\n<p>How can I change that default color??</p>",
    "PostedDate": "2009-05-15T04:55:25.747-07:00",
    "UserRole": null,
    "MarkedAsAnswerDate": null
  },
  {
    "Id": "190823",
    "ThreadId": "56428",
    "Html": "<p>Could you post a screenshot?&nbsp; I'm not sure which area you're referring to.&nbsp; Thanks!</p>",
    "PostedDate": "2009-05-15T10:45:59.887-07:00",
    "UserRole": null,
    "MarkedAsAnswerDate": null
  }
]