[
  {
    "Id": "222296",
    "ThreadId": "65269",
    "Html": "<p>I have a DataGrid, with the following relevant properties:<br>(I am using the release from June 25, 2009)&nbsp;</p>\r\n<p>&nbsp;</p>\r\n<div style=\"color:Black;background-color:White\">\r\n<pre><span style=\"color:Blue\">&lt;</span><span style=\"color:#A31515\">wt</span><span style=\"color:Blue\">:</span><span style=\"color:#A31515\">DataGrid</span>\r\n\t<span style=\"color:Red\">HeadersVisibility</span><span style=\"color:Blue\">=</span><span style=\"color:Black\">&quot;</span><span style=\"color:Blue\">All</span><span style=\"color:Black\">&quot;</span>\r\n\t<span style=\"color:Red\">AutoGenerateColumn</span><span style=\"color:Blue\">=</span><span style=\"color:Black\">&quot;</span><span style=\"color:Blue\">False</span><span style=\"color:Black\">&quot;</span>\r\n\t<span style=\"color:Blue\">&gt;</span>\r\n\t<span style=\"color:Blue\">&lt;</span><span style=\"color:#A31515\">wt</span><span style=\"color:Blue\">:</span><span style=\"color:#A31515\">DataGrid.RowHeaderStyle</span><span style=\"color:Blue\">&gt;</span>\r\n\t\t<span style=\"color:Blue\">&lt;</span><span style=\"color:#A31515\">Style</span> <span style=\"color:Red\">TargetType</span><span style=\"color:Blue\">=</span><span style=\"color:Black\">&quot;</span><span style=\"color:Blue\">{x:Type wtp:DataGridRowHeader}</span><span style=\"color:Black\">&quot;</span><span style=\"color:Blue\">&gt;</span>\r\n\t\t\t<span style=\"color:Blue\">&lt;</span><span style=\"color:#A31515\">Setter</span> <span style=\"color:Red\">Property</span><span style=\"color:Blue\">=</span><span style=\"color:Black\">&quot;</span><span style=\"color:Blue\">Content</span><span style=\"color:Black\">&quot;</span> <span style=\"color:Red\">Value</span><span style=\"color:Blue\">=</span><span style=\"color:Black\">&quot;</span><span style=\"color:Blue\">{Binding DisplayOrder}</span><span style=\"color:Black\">&quot;</span><span style=\"color:Blue\">/&gt;</span>\r\n\t\t<span style=\"color:Blue\">&lt;/</span><span style=\"color:#A31515\">Style</span><span style=\"color:Blue\">&gt;</span>\r\n\t<span style=\"color:Blue\">&lt;/</span><span style=\"color:#A31515\">wt</span><span style=\"color:Blue\">:</span><span style=\"color:#A31515\">DataGrid.RowHeaderStyle</span><span style=\"color:Blue\">&gt;</span>\r\n\t<span style=\"color:Green\">&lt;!-- .... other property .... --&gt;</span>\r\n<span style=\"color:Blue\">&lt;/</span><span style=\"color:#A31515\">wt</span><span style=\"color:Blue\">:</span><span style=\"color:#A31515\">DataGrid</span><span style=\"color:Blue\">&gt;</span>\r\n</pre>\r\n</div>\r\n<p>&nbsp;</p>\r\n<p>&nbsp;</p>\r\n<p>Now when it display the column headers are not aligned with the cell content, like that:<br><a href=\"http://dev.agtrix.net:8080/files/datagridcolumn.png\">http://dev.agtrix.net:8080/files/datagridcolumn.png</a></p>\r\n<p>Any tip on what I can do?</p>",
    "PostedDate": "2009-08-11T19:33:37.907-07:00",
    "UserRole": null,
    "MarkedAsAnswerDate": null
  }
]