[
  {
    "Id": "223458",
    "ThreadId": "65689",
    "Html": "<p>Hi</p>\r\n<p>Does anybody know&nbsp;a best practice to close a view in MVVM pattern keeping a code-behind empty.?</p>\r\n<p>Thanks</p>",
    "PostedDate": "2009-08-14T05:42:02.287-07:00",
    "UserRole": null,
    "MarkedAsAnswerDate": null
  },
  {
    "Id": "223462",
    "ThreadId": "65689",
    "Html": "<p>Take a look at this article here, <a href=\"http://blogs.msdn.com/vinsibal/archive/2009/04/10/launching-a-custom-dialog-to-edit-items-in-a-datagrid-with-mvvm.aspx\">http://blogs.msdn.com/vinsibal/archive/2009/04/10/launching-a-custom-dialog-to-edit-items-in-a-datagrid-with-mvvm.aspx</a>&nbsp;or this one here <a href=\"http://msdn.microsoft.com/en-us/magazine/dd419663.aspx\">http://msdn.microsoft.com/en-us/magazine/dd419663.aspx</a>.&nbsp; That should give you an idea of how to close a view using MVVM.</p>",
    "PostedDate": "2009-08-14T05:48:40.693-07:00",
    "UserRole": null,
    "MarkedAsAnswerDate": null
  },
  {
    "Id": "242231",
    "ThreadId": "65689",
    "Html": "<p>An alternative approach is shown in the ViewModel sample of the <strong><a href=\"http://waf.codeplex.com\">WPF Application Framework (WAF)</a></strong>.</p>",
    "PostedDate": "2009-10-05T09:08:47.813-07:00",
    "UserRole": null,
    "MarkedAsAnswerDate": null
  }
]