[
  {
    "Id": "236423",
    "ThreadId": "69475",
    "Html": "<p>Hi there,</p>\r\n<p>I have some problems binding within VisualState, imagine something like the code below. So, is there a way to bind the animation's Value property to anything at all?</p>\r\n<pre><span style=\"color:Blue\">&lt;ControlTemplate</span><span style=\"color:Blue\">&gt;<br>...</span></pre>\r\n<p>\r\n<div style=\"color:Black;background-color:White\">\r\n<pre><span style=\"color:Blue\">&lt;</span><span style=\"color:#A31515\">Storyboard</span><span style=\"color:Blue\">&gt;</span>\r\n<span style=\"color:Blue\">  &lt;</span><span style=\"color:#A31515\">ColorAnimationUsingKeyFrames</span> <span style=\"color:Red\">BeginTime</span><span style=\"color:Blue\">=</span><span style=\"color:Black\">&quot;</span><span style=\"color:Blue\">00:00:00</span><span style=\"color:Black\">&quot;</span> <span style=\"color:Red\">Duration</span><span style=\"color:Blue\">=</span><span style=\"color:Black\">&quot;</span><span style=\"color:Blue\">00:00:01.10000</span><span style=\"color:Black\">&quot;</span> <span style=\"color:Red\">Storyboard.TargetName</span><span style=\"color:Blue\">=</span><span style=\"color:Black\">&quot;</span><span style=\"color:Blue\">ellipse</span><span style=\"color:Black\">&quot;</span> <span style=\"color:Red\">Storyboard.TargetProperty</span><span style=\"color:Blue\">=</span><span style=\"color:Black\">&quot;</span><span style=\"color:Blue\">(Shape.Fill).(GradientBrush.GradientStops)[0].(GradientStop.Color)</span><span style=\"color:Black\">&quot;</span><span style=\"color:Blue\">&gt;</span>\r\n  <span style=\"color:Blue\">  &lt;</span><span style=\"color:#A31515\">SplineColorKeyFrame</span> <span style=\"color:Red\">KeyTime</span><span style=\"color:Blue\">=</span><span style=\"color:Black\">&quot;</span><span style=\"color:Blue\">00:00:00</span><span style=\"color:Black\">&quot;</span> <span style=\"color:Red\">Value</span><span style=\"color:Blue\">=</span><span style=\"color:Black\">&quot;</span><span style=\"color:Blue\">{Binding ElementName=Tubo, Path=Background}</span><span style=\"color:Black\">&quot;</span><span style=\"color:Blue\">/&gt;</span>\r\n<br>...<br><div style=\"color:Black;background-color:White\"><pre><span style=\"color:Blue\">&lt;</span><span style=\"color:#A31515\">Label</span> <span style=\"color:Red\">x:Name</span><span style=\"color:Blue\">=</span><span style=\"color:Black\">&quot;</span><span style=\"color:Blue\">Tubo</span><span style=\"color:Black\">&quot;</span> <span style=\"color:Red\">Background</span><span style=\"color:Blue\">=</span><span style=\"color:Black\">&quot;</span><span style=\"color:Blue\">Red</span><span style=\"color:Black\">&quot;</span> <span style=\"color:Red\">Visibility</span><span style=\"color:Blue\">=</span><span style=\"color:Black\">&quot;</span><span style=\"color:Blue\">Hidden</span><span style=\"color:Black\">&quot;</span> <span style=\"color:Blue\">/&gt;</span>\r\n<br></pre>\r\n</div>\r\n</pre>\r\n</div>\r\n</p>\r\n<pre><span style=\"color:Blue\">&lt;/ControlTemplate</span><span style=\"color:Blue\">&gt;</span></pre>",
    "PostedDate": "2009-09-19T09:14:05.047-07:00",
    "UserRole": null,
    "MarkedAsAnswerDate": null
  }
]