[
  {
    "Id": "240367",
    "ThreadId": "70568",
    "Html": "<p>Hi,</p>\r\n<p>&nbsp;&nbsp;&nbsp;&nbsp;&nbsp;&nbsp;&nbsp; Can anyone please tell me how to create the bar chart using the WPFToolKit binaries. I can able to create the Pie chart.But don't know how to create a bar chart.I mean the structure of coding both in XAML(UI) and C#(CodeBehind).</p>\r\n<p>&nbsp;</p>\r\n<p>Thanks,</p>\r\n<p>kumar.</p>",
    "PostedDate": "2009-09-30T05:14:58.21-07:00",
    "UserRole": null,
    "MarkedAsAnswerDate": null
  }
]