{
  "WorkItem": {
    "AffectedComponent": {
      "Name": "",
      "DisplayName": ""
    },
    "ClosedComment": "",
    "ClosedDate": null,
    "CommentCount": 0,
    "Custom": null,
    "Description": "The assembly version in AssemblyInfo.cs file is still 3.5.40128.1 and only AssemblyFileVersion has been updated.\nWhen you add a reference to WPFToolkit in Visual Studio, WPFToolkit is listed with the wrong version number and the wrong version number is used to create the manifest.",
    "LastUpdatedDate": "2013-02-21T18:40:44.42-08:00",
    "PlannedForRelease": "",
    "ReleaseVisibleToPublic": false,
    "Priority": {
      "Name": "Low",
      "Severity": 50,
      "Id": 1
    },
    "ProjectName": "wpf",
    "ReportedDate": "2010-02-25T17:07:32.12-08:00",
    "Status": {
      "Name": "Proposed",
      "Id": 1
    },
    "ReasonClosed": {
      "Name": "Unassigned"
    },
    "Summary": "Wrong Assembly version",
    "Type": {
      "Name": "Issue",
      "Id": 3
    },
    "VoteCount": 3,
    "Id": 11920
  },
  "FileAttachments": [],
  "Comments": []
}